{
	"IcoMoonType": "selection",
	"icons": [
		{
			"icon": {
				"paths": [
					"M409.6 921.6c-28.277 0-51.2-22.923-51.2-51.2v0c0-26.266 23.040-51.2 51.2-51.2h51.2v-51.2c-108.851-16.998-210.739-90.624-251.699-184.32-2.323-5.636-3.671-12.18-3.671-19.038 0-28.277 22.923-51.2 51.2-51.2 20.312 0 37.862 11.828 46.137 28.972l0.133 0.306c30.208 69.018 121.446 122.88 209.101 122.88 87.706 0 178.893-53.76 209.101-122.88 7.764-19.010 26.11-32.162 47.529-32.162 28.277 0 51.2 22.923 51.2 51.2 0 7.965-1.819 15.505-5.063 22.228l0.133-0.306c-40.909 93.696-142.848 167.322-251.699 184.32v51.2h51.2c28.277 0 51.2 22.923 51.2 51.2v0c0 26.266-23.040 51.2-51.2 51.2zM512 102.4c81.818 0 153.6 68.608 153.6 153.6v179.2c0 84.831-68.769 153.6-153.6 153.6v0c-81.818 0-153.6-68.608-153.6-153.6v-179.2c0-84.831 68.769-153.6 153.6-153.6v0z"
				],
				"attrs": [{}],
				"isMulticolor": false,
				"isMulticolor2": false,
				"grid": 0,
				"tags": ["db_ic_microphone_solid_20"]
			},
			"attrs": [{}],
			"properties": {
				"order": 90,
				"id": 5,
				"name": "db_ic_microphone_solid_20",
				"prevSize": 32,
				"code": 127908
			},
			"setIdx": 0,
			"setId": 1,
			"iconIdx": 0
		},
		{
			"icon": {
				"paths": [
					"M307.2 768.256v-510.464c0-29.082 24.986-52.992 52.992-52.992 9.984 0 18.944 3.021 27.955 9.011l394.086 227.738c22.989 16.026 36.966 41.984 36.966 69.939 0 28.006-13.978 53.965-36.966 69.939l-395.059 228.762c-8.123 5.579-18.152 8.937-28.96 9.011h-0.019c-24.986 0-50.995-19.968-50.995-50.944z"
				],
				"attrs": [{}],
				"isMulticolor": false,
				"isMulticolor2": false,
				"tags": ["play-filled"],
				"grid": 0
			},
			"attrs": [{}],
			"properties": {
				"order": 317,
				"id": 0,
				"name": "play-filled",
				"prevSize": 32,
				"code": 9655
			},
			"setIdx": 0,
			"setId": 1,
			"iconIdx": 1
		},
		{
			"icon": {
				"paths": [
					"M819.2 768.154v-511.334c0-26.010-19.968-51.046-52.019-52.019-10.845 0.064-20.894 3.423-29.208 9.126l0.178-0.115-317.645 228.147c-22.381 15.557-36.883 41.091-37.018 70.021v0.021c0 27.034 14.029 54.016 37.018 69.018l319.642 230.195c7.987 4.966 18.022 7.987 28.006 7.987 29.030 0 51.046-23.040 51.046-51.046zM306.893 717.158v-410.317c-0.116-28.135-22.907-50.908-51.038-50.995h-0.008c-28.058 0-51.046 23.040-51.046 51.046v410.266c0.116 28.135 22.907 50.908 51.038 50.995h0.008c28.006 0 51.046-23.040 51.046-50.995z"
				],
				"attrs": [{}],
				"isMulticolor": false,
				"isMulticolor2": false,
				"tags": ["skip-backward-filled"],
				"grid": 0
			},
			"attrs": [{}],
			"properties": {
				"order": 318,
				"id": 1,
				"name": "skip-backward-filled",
				"prevSize": 32,
				"code": 9198
			},
			"setIdx": 0,
			"setId": 1,
			"iconIdx": 2
		},
		{
			"icon": {
				"paths": [
					"M204.8 768.154v-511.334c0-26.010 19.968-50.995 52.019-52.019 10.035 0 20.019 3.021 29.030 9.011l317.645 228.147c23.040 16.026 37.018 41.984 37.018 70.042 0 27.034-14.029 54.016-37.018 69.018l-319.642 230.195c-7.966 4.981-17.636 7.949-27.996 7.987h-0.010c-0.138 0.001-0.3 0.002-0.463 0.002-27.938 0-50.586-22.648-50.586-50.586 0-0.163 0.001-0.325 0.002-0.488v0.025zM717.158 717.158v-410.317c0.116-28.117 22.878-50.879 50.984-50.995h0.011c28.006 0 51.046 23.040 51.046 51.046v410.266c-0.116 28.135-22.907 50.908-51.038 50.995h-0.008c-28.117-0.116-50.879-22.878-50.995-50.984v-0.011z"
				],
				"attrs": [{}],
				"isMulticolor": false,
				"isMulticolor2": false,
				"tags": ["skip-forward-filled"],
				"grid": 0
			},
			"attrs": [{}],
			"properties": {
				"order": 319,
				"id": 2,
				"name": "skip-forward-filled",
				"prevSize": 32,
				"code": 9197
			},
			"setIdx": 0,
			"setId": 1,
			"iconIdx": 3
		},
		{
			"icon": {
				"paths": [
					"M256 666.010v-308.019c0-56.013 45.978-101.99 103.014-101.99h306.995c56.234 0.232 101.759 45.756 101.99 101.968v307.017c0 0.107 0.001 0.234 0.001 0.361 0 56.462-45.582 102.277-101.955 102.654h-308.055c-56.234-0.232-101.759-45.756-101.99-101.968v-0.022z"
				],
				"attrs": [{}],
				"isMulticolor": false,
				"isMulticolor2": false,
				"tags": ["stop-filled"],
				"grid": 0
			},
			"attrs": [{}],
			"properties": {
				"order": 320,
				"id": 3,
				"name": "stop-filled",
				"prevSize": 32,
				"code": 9633
			},
			"setIdx": 0,
			"setId": 1,
			"iconIdx": 4
		},
		{
			"icon": {
				"paths": [
					"M819.2 204.8c57.6 0 102.4 46.387 102.4 102.4v409.6c0 56.013-44.8 102.4-102.4 102.4h-614.4c-56.013 0-102.4-46.387-102.4-102.4v-409.6c0-56.013 46.387-102.4 102.4-102.4h614.4zM817.613 614.4h-100.813v102.4h100.813v-102.4zM614.4 614.4h-409.6v102.4h409.6v-102.4z"
				],
				"attrs": [{}],
				"isMulticolor": false,
				"isMulticolor2": false,
				"tags": ["subtitles-filled"],
				"grid": 0
			},
			"attrs": [{}],
			"properties": {
				"order": 321,
				"id": 4,
				"name": "subtitles-filled",
				"prevSize": 32,
				"code": 921745
			},
			"setIdx": 0,
			"setId": 1,
			"iconIdx": 5
		}
	],
	"height": 1024,
	"metadata": {
		"name": "db-icons",
		"url": "https://db.de/db-ui",
		"designerURL": "https://marketingportal.extranet.deutschebahn.com/de/icons-2"
	},
	"preferences": {
		"showGlyphs": true,
		"showCodes": true,
		"showQuickUse": true,
		"showQuickUse2": true,
		"showSVGs": true,
		"fontPref": {
			"prefix": "icon-",
			"metadata": {
				"fontFamily": "db-icons",
				"majorVersion": 1,
				"minorVersion": 0,
				"designerURL": "https://marketingportal.extranet.deutschebahn.com/de/icons-2",
				"fontURL": "https://db.de/db-ui"
			},
			"metrics": { "emSize": 1024, "baseline": 6.25, "whitespace": 50 },
			"embed": false,
			"noie8": true,
			"ie7": false,
			"showSelector": true,
			"showMetrics": true,
			"showMetadata": true
		},
		"imagePref": {
			"prefix": "icon-",
			"png": true,
			"useClassSelector": true,
			"color": 0,
			"bgColor": 16777215,
			"name": "icomoon",
			"classSelector": ".icon"
		},
		"historySize": 50,
		"gridSize": 16,
		"showGrid": true
	}
}
